mediciasafely/VERSION
mediciasafely/__init__.py
mediciasafely/check.py
mediciasafely/codelists.py
mediciasafely/jupyter.py
mediciasafely/pull.py
mediciasafely/upgrade.py
mediciasafely/_vendor/jobrunner/__init__.py
mediciasafely/_vendor/jobrunner/config.py
mediciasafely/_vendor/jobrunner/create_or_update_jobs.py
mediciasafely/_vendor/jobrunner/job_executor.py
mediciasafely/_vendor/jobrunner/manage_jobs.py
mediciasafely/_vendor/jobrunner/manifest_to_database_migration.py
mediciasafely/_vendor/jobrunner/models.py
mediciasafely/_vendor/jobrunner/patients.py
mediciasafely/_vendor/jobrunner/project.py
mediciasafely/_vendor/jobrunner/queries.py
mediciasafely/_vendor/jobrunner/record_stats.py
mediciasafely/_vendor/jobrunner/reusable_actions.py
mediciasafely/_vendor/jobrunner/run.py
mediciasafely/_vendor/jobrunner/schema.sql
mediciasafely/_vendor/jobrunner/service.py
mediciasafely/_vendor/jobrunner/sync.py
mediciasafely/_vendor/jobrunner/cli/__init__.py
mediciasafely/_vendor/jobrunner/cli/add_job.py
mediciasafely/_vendor/jobrunner/cli/extract_stats.py
mediciasafely/_vendor/jobrunner/cli/kill_job.py
mediciasafely/_vendor/jobrunner/cli/local_run.py
mediciasafely/_vendor/jobrunner/cli/manifest_migration.py
mediciasafely/_vendor/jobrunner/cli/retry_job.py
mediciasafely/_vendor/jobrunner/executors/__init__.py
mediciasafely/_vendor/jobrunner/executors/local.py
mediciasafely/_vendor/jobrunner/executors/logging.py
mediciasafely/_vendor/jobrunner/lib/__init__.py
mediciasafely/_vendor/jobrunner/lib/database.py
mediciasafely/_vendor/jobrunner/lib/docker.py
mediciasafely/_vendor/jobrunner/lib/docker_stats.py
mediciasafely/_vendor/jobrunner/lib/git.py
mediciasafely/_vendor/jobrunner/lib/github_validators.py
mediciasafely/_vendor/jobrunner/lib/log_utils.py
mediciasafely/_vendor/jobrunner/lib/lru_dict.py
mediciasafely/_vendor/jobrunner/lib/path_utils.py
mediciasafely/_vendor/jobrunner/lib/string_utils.py
mediciasafely/_vendor/jobrunner/lib/subprocess_utils.py
mediciasafely-1.2.1.dist-info/LICENSE
mediciasafely-1.2.1.dist-info/METADATA
mediciasafely-1.2.1.dist-info/WHEEL
mediciasafely-1.2.1.dist-info/entry_points.txt
mediciasafely-1.2.1.dist-info/top_level.txt
mediciasafely-1.2.1.dist-info/RECORD
