Metadata-Version: 2.1
Name: mediciasafely
Version: 1.2.1
Summary: Command line tool for running MediciaSAFELY studies locally.
Home-page: https://github.com/mediciaai/mediciasafely-cli
Author: MediciaSAFELY
Author-email: frankie@medicia.ai
License: GPLv3
Project-URL: Homepage, https://www.medicia.ai
Project-URL: Documentation, https://docs.opensafely.org
Platform: UNKNOWN
Classifier: License :: OSI Approved :: GNU General Public License v3 (GPLv3)
Requires-Python: >=3.8
License-File: LICENSE
